{".class": "MypyFile", "_fullname": "structure.graph_utils", "_name": null, "is_stub": false, "names": {".class": "SymbolTable", "GraphMaker": {".class": "SymbolTableNode", "kind": "Gdef", "node": {".class": "Var", "flags": ["is_ready", "is_suppressed_import"], "fullname": "structure.graph_utils.GraphMaker", "name": "GraphMaker", "type": {".class": "AnyType"}}}, "Tuple": {".class": "SymbolTableNode", "cross_ref": "typing.Tuple", "kind": "Gdef"}, "__doc__": {".class": "SymbolTableNode", "kind": "Gdef", "node": {".class": "Var", "flags": ["is_ready"], "fullname": "structure.graph_utils.__doc__", "name": "__doc__", "type": "builtins.str"}}, "__file__": {".class": "SymbolTableNode", "kind": "Gdef", "node": {".class": "Var", "flags": ["is_ready"], "fullname": "structure.graph_utils.__file__", "name": "__file__", "type": "builtins.str"}}, "__name__": {".class": "SymbolTableNode", "kind": "Gdef", "node": {".class": "Var", "flags": ["is_ready"], "fullname": "structure.graph_utils.__name__", "name": "__name__", "type": "builtins.str"}}, "__package__": {".class": "SymbolTableNode", "kind": "Gdef", "node": {".class": "Var", "flags": ["is_ready"], "fullname": "structure.graph_utils.__package__", "name": "__package__", "type": "builtins.str"}}, "angle": {".class": "SymbolTableNode", "kind": "Gdef", "node": {".class": "Var", "flags": ["is_ready", "is_suppressed_import"], "fullname": "structure.graph_utils.angle", "name": "angle", "type": {".class": "AnyType"}}}, "ase": {".class": "SymbolTableNode", "kind": "Gdef", "node": {".class": "Var", "flags": ["is_ready", "is_suppressed_import"], "fullname": "structure.graph_utils.ase", "name": "ase", "type": {".class": "AnyType"}}}, "collections": {".class": "SymbolTableNode", "cross_ref": "collections", "kind": "ModuleRef"}, "dihedral": {".class": "SymbolTableNode", "kind": "Gdef", "node": {".class": "Var", "flags": ["is_ready", "is_suppressed_import"], "fullname": "structure.graph_utils.dihedral", "name": "dihedral", "type": {".class": "AnyType"}}}, "flatten": {".class": "SymbolTableNode", "kind": "Gdef", "node": {".class": "Var", "flags": ["is_ready", "is_suppressed_import"], "fullname": "structure.graph_utils.flatten", "name": "flatten", "type": {".class": "AnyType"}}}, "get_angles": {".class": "SymbolTableNode", "kind": "Gdef", "node": {".class": "FuncDef", "arg_kinds": [0], "arg_names": ["g"], "flags": [], "fullname": "structure.graph_utils.get_angles", "name": "get_angles", "type": {".class": "CallableType", "arg_kinds": [0], "arg_names": ["g"], "arg_types": [{".class": "AnyType"}], "bound_args": [], "fallback": "builtins.function", "implicit": false, "is_classmethod_class": false, "is_ellipsis_args": false, "name": "get_angles", "ret_type": {".class": "Instance", "args": [{".class": "AnyType"}, {".class": "AnyType"}], "type_ref": "builtins.dict"}, "variables": []}}}, "get_dihedrals": {".class": "SymbolTableNode", "kind": "Gdef", "node": {".class": "FuncDef", "arg_kinds": [0], "arg_names": ["g"], "flags": [], "fullname": "structure.graph_utils.get_dihedrals", "name": "get_dihedrals", "type": {".class": "CallableType", "arg_kinds": [0], "arg_names": ["g"], "arg_types": [{".class": "AnyType"}], "bound_args": [], "fallback": "builtins.function", "implicit": false, "is_classmethod_class": false, "is_ellipsis_args": false, "name": "get_dihedrals", "ret_type": {".class": "Instance", "args": [{".class": "AnyType"}, {".class": "AnyType"}], "type_ref": "builtins.dict"}, "variables": []}}}, "get_graph_diff": {".class": "SymbolTableNode", "kind": "Gdef", "node": {".class": "FuncDef", "arg_kinds": [0, 1, 1, 1, 1, 1], "arg_names": ["stordir", "trajname", "stordir2", "trajname2", "graphmaker", "graphmaker2"], "flags": [], "fullname": "structure.graph_utils.get_graph_diff", "name": "get_graph_diff", "type": {".class": "CallableType", "arg_kinds": [0, 1, 1, 1, 1, 1], "arg_names": ["stordir", "trajname", "stordir2", "trajname2", "graphmaker", "graphmaker2"], "arg_types": ["builtins.str", "builtins.str", {".class": "UnionType", "items": ["builtins.str", {".class": "NoneTyp"}]}, {".class": "UnionType", "items": ["builtins.str", {".class": "NoneTyp"}]}, {".class": "AnyType"}, {".class": "AnyType"}], "bound_args": [], "fallback": "builtins.function", "implicit": false, "is_classmethod_class": false, "is_ellipsis_args": false, "name": "get_graph_diff", "ret_type": {".class": "TupleType", "fallback": {".class": "Instance", "args": [{".class": "AnyType"}], "type_ref": "builtins.tuple"}, "implicit": false, "items": [{".class": "AnyType"}, {".class": "AnyType"}]}, "variables": []}}}, "graph_diff": {".class": "SymbolTableNode", "kind": "Gdef", "node": {".class": "FuncDef", "arg_kinds": [0, 0], "arg_names": ["G", "H"], "flags": [], "fullname": "structure.graph_utils.graph_diff", "name": "graph_diff", "type": {".class": "CallableType", "arg_kinds": [0, 0], "arg_names": ["G", "H"], "arg_types": [{".class": "AnyType"}, {".class": "AnyType"}], "bound_args": [], "fallback": "builtins.function", "implicit": false, "is_classmethod_class": false, "is_ellipsis_args": false, "name": "graph_diff", "ret_type": {".class": "AnyType"}, "variables": []}}}, "graph_summary": {".class": "SymbolTableNode", "kind": "Gdef", "node": {".class": "FuncDef", "arg_kinds": [0, 1], "arg_names": ["G", "name"], "flags": [], "fullname": "structure.graph_utils.graph_summary", "name": "graph_summary", "type": {".class": "CallableType", "arg_kinds": [0, 1], "arg_names": ["G", "name"], "arg_types": [{".class": "AnyType"}, "builtins.str"], "bound_args": [], "fallback": "builtins.function", "implicit": false, "is_classmethod_class": false, "is_ellipsis_args": false, "name": "graph_summary", "ret_type": {".class": "NoneTyp"}, "variables": []}}}, "is_isomorphic": {".class": "SymbolTableNode", "kind": "Gdef", "node": {".class": "FuncDef", "arg_kinds": [0, 1, 1, 1, 1, 1], "arg_names": ["stordir", "trajname", "stordir2", "trajname2", "graphmaker", "graphmaker2"], "flags": [], "fullname": "structure.graph_utils.is_isomorphic", "name": "is_isomorphic", "type": {".class": "CallableType", "arg_kinds": [0, 1, 1, 1, 1, 1], "arg_names": ["stordir", "trajname", "stordir2", "trajname2", "graphmaker", "graphmaker2"], "arg_types": ["builtins.str", "builtins.str", {".class": "UnionType", "items": ["builtins.str", {".class": "NoneTyp"}]}, {".class": "UnionType", "items": ["builtins.str", {".class": "NoneTyp"}]}, {".class": "UnionType", "items": [{".class": "AnyType"}, {".class": "NoneTyp"}]}, {".class": "UnionType", "items": [{".class": "AnyType"}, {".class": "NoneTyp"}]}], "bound_args": [], "fallback": "builtins.function", "implicit": false, "is_classmethod_class": false, "is_ellipsis_args": false, "name": "is_isomorphic", "ret_type": {".class": "AnyType"}, "variables": []}}}, "is_subgraph": {".class": "SymbolTableNode", "kind": "Gdef", "node": {".class": "FuncDef", "arg_kinds": [0, 0, 1], "arg_names": ["big", "small", "ignore_metals"], "flags": [], "fullname": "structure.graph_utils.is_subgraph", "name": "is_subgraph", "type": {".class": "CallableType", "arg_kinds": [0, 0, 1], "arg_names": ["big", "small", "ignore_metals"], "arg_types": [{".class": "AnyType"}, {".class": "AnyType"}, "builtins.bool"], "bound_args": [], "fallback": "builtins.function", "implicit": false, "is_classmethod_class": false, "is_ellipsis_args": false, "name": "is_subgraph", "ret_type": "builtins.bool", "variables": []}}}, "iso": {".class": "SymbolTableNode", "kind": "Gdef", "node": {".class": "Var", "flags": ["is_ready", "is_suppressed_import"], "fullname": "structure.graph_utils.iso", "name": "iso", "type": {".class": "AnyType"}}}, "make_subgraph": {".class": "SymbolTableNode", "kind": "Gdef", "node": {".class": "FuncDef", "arg_kinds": [0, 0, 0], "arg_names": ["graph", "index", "pathlength"], "flags": [], "fullname": "structure.graph_utils.make_subgraph", "name": "make_subgraph", "type": {".class": "CallableType", "arg_kinds": [0, 0, 0], "arg_names": ["graph", "index", "pathlength"], "arg_types": [{".class": "AnyType"}, "builtins.int", "builtins.int"], "bound_args": [], "fallback": "builtins.function", "implicit": false, "is_classmethod_class": false, "is_ellipsis_args": false, "name": "make_subgraph", "ret_type": {".class": "AnyType"}, "variables": []}}}, "match_indices": {".class": "SymbolTableNode", "kind": "Gdef", "node": {".class": "Var", "flags": ["is_ready", "is_suppressed_import"], "fullname": "structure.graph_utils.match_indices", "name": "match_indices", "type": {".class": "AnyType"}}}, "metal_independent": {".class": "SymbolTableNode", "kind": "Gdef", "node": {".class": "FuncDef", "arg_kinds": [0], "arg_names": ["g"], "flags": [], "fullname": "structure.graph_utils.metal_independent", "name": "metal_independent", "type": {".class": "CallableType", "arg_kinds": [0], "arg_names": ["g"], "arg_types": [{".class": "AnyType"}], "bound_args": [], "fallback": "builtins.function", "implicit": false, "is_classmethod_class": false, "is_ellipsis_args": false, "name": "metal_independent", "ret_type": {".class": "AnyType"}, "variables": []}}}, "nonmetals": {".class": "SymbolTableNode", "kind": "Gdef", "node": {".class": "Var", "flags": ["is_ready", "is_suppressed_import"], "fullname": "structure.graph_utils.nonmetals", "name": "nonmetals", "type": {".class": "AnyType"}}}, "nx": {".class": "SymbolTableNode", "kind": "Gdef", "node": {".class": "Var", "flags": ["is_ready", "is_suppressed_import"], "fullname": "structure.graph_utils.nx", "name": "nx", "type": {".class": "AnyType"}}}, "old_graph_diff": {".class": "SymbolTableNode", "kind": "Gdef", "node": {".class": "FuncDef", "arg_kinds": [0, 0], "arg_names": ["G", "H"], "flags": [], "fullname": "structure.graph_utils.old_graph_diff", "name": "old_graph_diff", "type": {".class": "CallableType", "arg_kinds": [0, 0], "arg_names": ["G", "H"], "arg_types": [{".class": "AnyType"}, {".class": "AnyType"}], "bound_args": [], "fallback": "builtins.function", "implicit": false, "is_classmethod_class": false, "is_ellipsis_args": false, "name": "old_graph_diff", "ret_type": {".class": "AnyType"}, "variables": []}}}, "reorder_nodes": {".class": "SymbolTableNode", "kind": "Gdef", "node": {".class": "FuncDef", "arg_kinds": [0, 0], "arg_names": ["graph", "mapping_dict"], "flags": [], "fullname": "structure.graph_utils.reorder_nodes", "name": "reorder_nodes", "type": {".class": "CallableType", "arg_kinds": [0, 0], "arg_names": ["graph", "mapping_dict"], "arg_types": [{".class": "AnyType"}, {".class": "Instance", "args": [{".class": "AnyType"}, {".class": "AnyType"}], "type_ref": "builtins.dict"}], "bound_args": [], "fallback": "builtins.function", "implicit": false, "is_classmethod_class": false, "is_ellipsis_args": false, "name": "reorder_nodes", "ret_type": {".class": "AnyType"}, "variables": []}}}, "to_atoms": {".class": "SymbolTableNode", "kind": "Gdef", "node": {".class": "FuncDef", "arg_kinds": [0], "arg_names": ["g"], "flags": [], "fullname": "structure.graph_utils.to_atoms", "name": "to_atoms", "type": {".class": "CallableType", "arg_kinds": [0], "arg_names": ["g"], "arg_types": [{".class": "AnyType"}], "bound_args": [], "fallback": "builtins.function", "implicit": false, "is_classmethod_class": false, "is_ellipsis_args": false, "name": "to_atoms", "ret_type": {".class": "AnyType"}, "variables": []}}}}, "path": "/Users/kbrown/graphatoms/structure/graph_utils.py"}
