{".class": "MypyFile", "_fullname": "graphatoms.structure.graph", "_name": null, "is_stub": false, "names": {".class": "SymbolTable", "Callable": {".class": "SymbolTableNode", "cross_ref": "typing.Callable", "kind": "Gdef"}, "Dict": {".class": "SymbolTableNode", "cross_ref": "builtins.dict", "kind": "Gdef", "normalized": true}, "Edge": {".class": "SymbolTableNode", "kind": "Gdef", "node": {".class": "TypeInfo", "_promote": null, "abstract_attributes": [], "bases": ["builtins.object"], "declared_metaclass": null, "defn": {".class": "ClassDef", "fullname": "graphatoms.structure.graph.Edge", "name": "Edge", "type_vars": []}, "flags": [], "fullname": "graphatoms.structure.graph.Edge", "metaclass_type": null, "module_name": "graphatoms.structure.graph", "names": {".class": "SymbolTable", "__init__": {".class": "SymbolTableNode", "kind": "Mdef", "node": {".class": "FuncDef", "arg_kinds": [0, 0, 0, 0, 0, 0, 1], "arg_names": ["self", "fromNode", "toNode", "distance", "offset", "bondorder", "vector"], "flags": [], "fullname": "graphatoms.structure.graph.Edge.__init__", "name": "__init__", "type": {".class": "CallableType", "arg_kinds": [0, 0, 0, 0, 0, 0, 1], "arg_names": ["self", "fromNode", "toNode", "distance", "offset", "bondorder", "vector"], "arg_types": ["graphatoms.structure.graph.Edge", "builtins.int", "builtins.int", "builtins.float", {".class": "Instance", "args": ["builtins.int"], "type_ref": "builtins.list"}, "builtins.float", {".class": "UnionType", "items": [{".class": "AnyType"}, {".class": "NoneTyp"}]}], "bound_args": [], "fallback": "builtins.function", "implicit": false, "is_classmethod_class": false, "is_ellipsis_args": false, "name": "__init__ of Edge", "ret_type": {".class": "NoneTyp"}, "variables": []}}}, "__repr__": {".class": "SymbolTableNode", "kind": "Mdef", "node": {".class": "FuncDef", "arg_kinds": [0], "arg_names": ["self"], "flags": [], "fullname": "graphatoms.structure.graph.Edge.__repr__", "name": "__repr__", "type": {".class": "CallableType", "arg_kinds": [0], "arg_names": [null], "arg_types": ["graphatoms.structure.graph.Edge"], "bound_args": [], "fallback": "builtins.function", "implicit": false, "is_classmethod_class": false, "is_ellipsis_args": false, "name": "__repr__ of Edge", "ret_type": "builtins.str", "variables": []}}}, "__str__": {".class": "SymbolTableNode", "kind": "Mdef", "node": {".class": "FuncDef", "arg_kinds": [0], "arg_names": ["self"], "flags": [], "fullname": "graphatoms.structure.graph.Edge.__str__", "name": "__str__", "type": {".class": "CallableType", "arg_kinds": [0], "arg_names": [null], "arg_types": ["graphatoms.structure.graph.Edge"], "bound_args": [], "fallback": "builtins.function", "implicit": false, "is_classmethod_class": false, "is_ellipsis_args": false, "name": "__str__ of Edge", "ret_type": "builtins.str", "variables": []}}}, "add_edge_to_graph": {".class": "SymbolTableNode", "kind": "Mdef", "node": {".class": "FuncDef", "arg_kinds": [0, 0], "arg_names": ["self", "grph"], "flags": [], "fullname": "graphatoms.structure.graph.Edge.add_edge_to_graph", "name": "add_edge_to_graph", "type": {".class": "CallableType", "arg_kinds": [0, 0], "arg_names": ["self", "grph"], "arg_types": ["graphatoms.structure.graph.Edge", {".class": "AnyType"}], "bound_args": [], "fallback": "builtins.function", "implicit": false, "is_classmethod_class": false, "is_ellipsis_args": false, "name": "add_edge_to_graph of Edge", "ret_type": {".class": "NoneTyp"}, "variables": []}}}, "bondorder": {".class": "SymbolTableNode", "implicit": true, "kind": "Mdef", "node": {".class": "Var", "flags": [], "fullname": "graphatoms.structure.graph.Edge.bondorder", "name": "bondorder", "type": "builtins.float"}}, "fromNode": {".class": "SymbolTableNode", "implicit": true, "kind": "Mdef", "node": {".class": "Var", "flags": [], "fullname": "graphatoms.structure.graph.Edge.fromNode", "name": "fromNode", "type": "builtins.int"}}, "inds_pbc": {".class": "SymbolTableNode", "kind": "Mdef", "node": {".class": "FuncDef", "arg_kinds": [0], "arg_names": ["self"], "flags": [], "fullname": "graphatoms.structure.graph.Edge.inds_pbc", "name": "inds_pbc", "type": {".class": "CallableType", "arg_kinds": [0], "arg_names": ["self"], "arg_types": ["graphatoms.structure.graph.Edge"], "bound_args": [], "fallback": "builtins.function", "implicit": false, "is_classmethod_class": false, "is_ellipsis_args": false, "name": "inds_pbc of Edge", "ret_type": {".class": "TupleType", "fallback": {".class": "Instance", "args": [{".class": "AnyType"}], "type_ref": "builtins.tuple"}, "implicit": false, "items": ["builtins.int", "builtins.int", {".class": "Instance", "args": ["builtins.int"], "type_ref": "builtins.list"}]}, "variables": []}}}, "pbc_shift": {".class": "SymbolTableNode", "implicit": true, "kind": "Mdef", "node": {".class": "Var", "flags": [], "fullname": "graphatoms.structure.graph.Edge.pbc_shift", "name": "pbc_shift", "type": {".class": "Instance", "args": ["builtins.int"], "type_ref": "builtins.list"}}}, "toNode": {".class": "SymbolTableNode", "implicit": true, "kind": "Mdef", "node": {".class": "Var", "flags": [], "fullname": "graphatoms.structure.graph.Edge.toNode", "name": "toNode", "type": "builtins.int"}}, "vector": {".class": "SymbolTableNode", "implicit": true, "kind": "Mdef", "node": {".class": "Var", "flags": [], "fullname": "graphatoms.structure.graph.Edge.vector", "name": "vector", "type": {".class": "UnionType", "items": [{".class": "AnyType"}, {".class": "NoneTyp"}]}}}, "weight": {".class": "SymbolTableNode", "implicit": true, "kind": "Mdef", "node": {".class": "Var", "flags": [], "fullname": "graphatoms.structure.graph.Edge.weight", "name": "weight", "type": "builtins.float"}}}, "protocol_members": null, "tuple_type": null, "type_vars": [], "typeddict_type": null}}, "GraphInput": {".class": "SymbolTableNode", "kind": "Gdef", "node": {".class": "TypeInfo", "_promote": null, "abstract_attributes": [], "bases": ["builtins.object"], "declared_metaclass": null, "defn": {".class": "ClassDef", "fullname": "graphatoms.structure.graph.GraphInput", "name": "GraphInput", "type_vars": []}, "flags": [], "fullname": "graphatoms.structure.graph.GraphInput", "metaclass_type": null, "module_name": "graphatoms.structure.graph", "names": {".class": "SymbolTable", "__init__": {".class": "SymbolTableNode", "kind": "Mdef", "node": {".class": "FuncDef", "arg_kinds": [0, 0, 0, 1], "arg_names": ["self", "stordir", "trajname", "atoms"], "flags": [], "fullname": "graphatoms.structure.graph.GraphInput.__init__", "name": "__init__", "type": {".class": "CallableType", "arg_kinds": [0, 0, 0, 1], "arg_names": ["self", "stordir", "trajname", "atoms"], "arg_types": ["graphatoms.structure.graph.GraphInput", "builtins.str", "builtins.str", {".class": "UnionType", "items": [{".class": "AnyType"}, {".class": "NoneTyp"}]}], "bound_args": [], "fallback": "builtins.function", "implicit": false, "is_classmethod_class": false, "is_ellipsis_args": false, "name": "__init__ of GraphInput", "ret_type": {".class": "NoneTyp"}, "variables": []}}}, "__repr__": {".class": "SymbolTableNode", "kind": "Mdef", "node": {".class": "FuncDef", "arg_kinds": [0], "arg_names": ["self"], "flags": [], "fullname": "graphatoms.structure.graph.GraphInput.__repr__", "name": "__repr__", "type": {".class": "CallableType", "arg_kinds": [0], "arg_names": [null], "arg_types": ["graphatoms.structure.graph.GraphInput"], "bound_args": [], "fallback": "builtins.function", "implicit": false, "is_classmethod_class": false, "is_ellipsis_args": false, "name": "__repr__ of GraphInput", "ret_type": "builtins.str", "variables": []}}}, "__str__": {".class": "SymbolTableNode", "kind": "Mdef", "node": {".class": "FuncDef", "arg_kinds": [0], "arg_names": ["self"], "flags": [], "fullname": "graphatoms.structure.graph.GraphInput.__str__", "name": "__str__", "type": {".class": "CallableType", "arg_kinds": [0], "arg_names": [null], "arg_types": ["graphatoms.structure.graph.GraphInput"], "bound_args": [], "fallback": "builtins.function", "implicit": false, "is_classmethod_class": false, "is_ellipsis_args": false, "name": "__str__ of GraphInput", "ret_type": "builtins.str", "variables": []}}}, "atoms": {".class": "SymbolTableNode", "implicit": true, "kind": "Mdef", "node": {".class": "Var", "flags": [], "fullname": "graphatoms.structure.graph.GraphInput.atoms", "name": "atoms", "type": {".class": "UnionType", "items": [{".class": "AnyType"}, {".class": "NoneTyp"}]}}}, "onlytraj": {".class": "SymbolTableNode", "implicit": true, "kind": "Mdef", "node": {".class": "Var", "flags": [], "fullname": "graphatoms.structure.graph.GraphInput.onlytraj", "name": "onlytraj", "type": "builtins.bool"}}, "stordir": {".class": "SymbolTableNode", "implicit": true, "kind": "Mdef", "node": {".class": "Var", "flags": [], "fullname": "graphatoms.structure.graph.GraphInput.stordir", "name": "stordir", "type": "builtins.str"}}, "trajname": {".class": "SymbolTableNode", "implicit": true, "kind": "Mdef", "node": {".class": "Var", "flags": [], "fullname": "graphatoms.structure.graph.GraphInput.trajname", "name": "trajname", "type": "builtins.str"}}, "view_atoms": {".class": "SymbolTableNode", "kind": "Mdef", "node": {".class": "FuncDef", "arg_kinds": [0], "arg_names": ["self"], "flags": [], "fullname": "graphatoms.structure.graph.GraphInput.view_atoms", "name": "view_atoms", "type": {".class": "CallableType", "arg_kinds": [0], "arg_names": ["self"], "arg_types": ["graphatoms.structure.graph.GraphInput"], "bound_args": [], "fallback": "builtins.function", "implicit": false, "is_classmethod_class": false, "is_ellipsis_args": false, "name": "view_atoms of GraphInput", "ret_type": {".class": "NoneTyp"}, "variables": []}}}}, "protocol_members": null, "tuple_type": null, "type_vars": [], "typeddict_type": null}}, "GraphMaker": {".class": "SymbolTableNode", "kind": "Gdef", "node": {".class": "TypeInfo", "_promote": null, "abstract_attributes": [], "bases": ["builtins.object"], "declared_metaclass": null, "defn": {".class": "ClassDef", "fullname": "graphatoms.structure.graph.GraphMaker", "name": "GraphMaker", "type_vars": []}, "flags": [], "fullname": "graphatoms.structure.graph.GraphMaker", "metaclass_type": null, "module_name": "graphatoms.structure.graph", "names": {".class": "SymbolTable", "__init__": {".class": "SymbolTableNode", "kind": "Mdef", "node": {".class": "FuncDef", "arg_kinds": [0, 1, 1, 1, 1], "arg_names": ["self", "include_frac", "group_cut", "min_bo", "jmol"], "flags": [], "fullname": "graphatoms.structure.graph.GraphMaker.__init__", "name": "__init__", "type": {".class": "CallableType", "arg_kinds": [0, 1, 1, 1, 1], "arg_names": ["self", "include_frac", "group_cut", "min_bo", "jmol"], "arg_types": ["graphatoms.structure.graph.GraphMaker", "builtins.float", "builtins.float", "builtins.float", "builtins.float"], "bound_args": [], "fallback": "builtins.function", "implicit": false, "is_classmethod_class": false, "is_ellipsis_args": false, "name": "__init__ of GraphMaker", "ret_type": {".class": "NoneTyp"}, "variables": []}}}, "_get_edge_dicts": {".class": "SymbolTableNode", "kind": "Mdef", "node": {".class": "FuncDef", "arg_kinds": [0, 0], "arg_names": ["self", "gi"], "flags": [], "fullname": "graphatoms.structure.graph.GraphMaker._get_edge_dicts", "name": "_get_edge_dicts", "type": {".class": "CallableType", "arg_kinds": [0, 0], "arg_names": ["self", "gi"], "arg_types": ["graphatoms.structure.graph.GraphMaker", "graphatoms.structure.graph.GraphInput"], "bound_args": [], "fallback": "builtins.function", "implicit": false, "is_classmethod_class": false, "is_ellipsis_args": false, "name": "_get_edge_dicts of GraphMaker", "ret_type": {".class": "Instance", "args": [{".class": "Instance", "args": [{".class": "AnyType"}, {".class": "AnyType"}], "type_ref": "builtins.dict"}], "type_ref": "builtins.list"}, "variables": []}}}, "_get_filtered_edges": {".class": "SymbolTableNode", "kind": "Mdef", "node": {".class": "FuncDef", "arg_kinds": [0, 0], "arg_names": ["self", "gi"], "flags": [], "fullname": "graphatoms.structure.graph.GraphMaker._get_filtered_edges", "name": "_get_filtered_edges", "type": {".class": "CallableType", "arg_kinds": [0, 0], "arg_names": ["self", "gi"], "arg_types": ["graphatoms.structure.graph.GraphMaker", "graphatoms.structure.graph.GraphInput"], "bound_args": [], "fallback": "builtins.function", "implicit": false, "is_classmethod_class": false, "is_ellipsis_args": false, "name": "_get_filtered_edges of GraphMaker", "ret_type": {".class": "Instance", "args": ["graphatoms.structure.graph.Edge"], "type_ref": "builtins.list"}, "variables": []}}}, "_get_sum_of_bond_order_data": {".class": "SymbolTableNode", "kind": "Mdef", "node": {".class": "FuncDef", "arg_kinds": [0, 0, 1], "arg_names": ["self", "gi", "show_indices"], "flags": [], "fullname": "graphatoms.structure.graph.GraphMaker._get_sum_of_bond_order_data", "name": "_get_sum_of_bond_order_data", "type": {".class": "CallableType", "arg_kinds": [0, 0, 1], "arg_names": ["self", "gi", "show_indices"], "arg_types": ["graphatoms.structure.graph.GraphMaker", "graphatoms.structure.graph.GraphInput", {".class": "UnionType", "items": [{".class": "Instance", "args": ["builtins.int"], "type_ref": "builtins.list"}, {".class": "NoneTyp"}]}], "bound_args": [], "fallback": "builtins.function", "implicit": false, "is_classmethod_class": false, "is_ellipsis_args": false, "name": "_get_sum_of_bond_order_data of GraphMaker", "ret_type": {".class": "TupleType", "fallback": {".class": "Instance", "args": [{".class": "AnyType"}], "type_ref": "builtins.tuple"}, "implicit": false, "items": [{".class": "Instance", "args": ["builtins.str"], "type_ref": "builtins.list"}, {".class": "AnyType"}]}, "variables": []}}}, "_graph_to_pybliss": {".class": "SymbolTableNode", "kind": "Mdef", "node": {".class": "FuncDef", "arg_kinds": [0, 0], "arg_names": ["self", "gi"], "flags": [], "fullname": "graphatoms.structure.graph.GraphMaker._graph_to_pybliss", "name": "_graph_to_pybliss", "type": {".class": "CallableType", "arg_kinds": [0, 0], "arg_names": ["self", "gi"], "arg_types": ["graphatoms.structure.graph.GraphMaker", "graphatoms.structure.graph.GraphInput"], "bound_args": [], "fallback": "builtins.function", "implicit": false, "is_classmethod_class": false, "is_ellipsis_args": false, "name": "_graph_to_pybliss of GraphMaker", "ret_type": {".class": "AnyType"}, "variables": []}}}, "_make_adjacency_matrix": {".class": "SymbolTableNode", "kind": "Mdef", "node": {".class": "FuncDef", "arg_kinds": [0, 0], "arg_names": ["self", "gi"], "flags": [], "fullname": "graphatoms.structure.graph.GraphMaker._make_adjacency_matrix", "name": "_make_adjacency_matrix", "type": {".class": "CallableType", "arg_kinds": [0, 0], "arg_names": ["self", "gi"], "arg_types": ["graphatoms.structure.graph.GraphMaker", "graphatoms.structure.graph.GraphInput"], "bound_args": [], "fallback": "builtins.function", "implicit": false, "is_classmethod_class": false, "is_ellipsis_args": false, "name": "_make_adjacency_matrix of GraphMaker", "ret_type": {".class": "AnyType"}, "variables": []}}}, "_make_edges": {".class": "SymbolTableNode", "kind": "Mdef", "node": {".class": "FuncDef", "arg_kinds": [0, 0], "arg_names": ["self", "gi"], "flags": [], "fullname": "graphatoms.structure.graph.GraphMaker._make_edges", "name": "_make_edges", "type": {".class": "CallableType", "arg_kinds": [0, 0], "arg_names": ["self", "gi"], "arg_types": ["graphatoms.structure.graph.GraphMaker", "graphatoms.structure.graph.GraphInput"], "bound_args": [], "fallback": "builtins.function", "implicit": false, "is_classmethod_class": false, "is_ellipsis_args": false, "name": "_make_edges of GraphMaker", "ret_type": {".class": "Instance", "args": ["builtins.int", {".class": "Instance", "args": ["graphatoms.structure.graph.Edge"], "type_ref": "builtins.list"}], "type_ref": "builtins.dict"}, "variables": []}}}, "_make_group": {".class": "SymbolTableNode", "kind": "Mdef", "node": {".class": "FuncDef", "arg_kinds": [0, 0, 1], "arg_names": ["self", "edge_list", "group_cut"], "flags": [], "fullname": "graphatoms.structure.graph.GraphMaker._make_group", "name": "_make_group", "type": {".class": "CallableType", "arg_kinds": [0, 0, 1], "arg_names": ["self", "edge_list", "group_cut"], "arg_types": ["graphatoms.structure.graph.GraphMaker", {".class": "Instance", "args": ["graphatoms.structure.graph.Edge"], "type_ref": "builtins.list"}, {".class": "UnionType", "items": ["builtins.float", {".class": "NoneTyp"}]}], "bound_args": [], "fallback": "builtins.function", "implicit": false, "is_classmethod_class": false, "is_ellipsis_args": false, "name": "_make_group of GraphMaker", "ret_type": {".class": "Instance", "args": [{".class": "Instance", "args": ["graphatoms.structure.graph.Edge"], "type_ref": "builtins.list"}], "type_ref": "builtins.list"}, "variables": []}}}, "colored": {".class": "SymbolTableNode", "implicit": true, "kind": "Mdef", "node": {".class": "Var", "flags": [], "fullname": "graphatoms.structure.graph.GraphMaker.colored", "name": "colored", "type": "builtins.bool"}}, "group_cut": {".class": "SymbolTableNode", "implicit": true, "kind": "Mdef", "node": {".class": "Var", "flags": [], "fullname": "graphatoms.structure.graph.GraphMaker.group_cut", "name": "group_cut", "type": "builtins.float"}}, "include_frac": {".class": "SymbolTableNode", "implicit": true, "kind": "Mdef", "node": {".class": "Var", "flags": [], "fullname": "graphatoms.structure.graph.GraphMaker.include_frac", "name": "include_frac", "type": "builtins.float"}}, "jmol": {".class": "SymbolTableNode", "implicit": true, "kind": "Mdef", "node": {".class": "Var", "flags": [], "fullname": "graphatoms.structure.graph.GraphMaker.jmol", "name": "jmol", "type": "builtins.float"}}, "make_graph": {".class": "SymbolTableNode", "kind": "Mdef", "node": {".class": "FuncDef", "arg_kinds": [0, 0], "arg_names": ["self", "gi"], "flags": [], "fullname": "graphatoms.structure.graph.GraphMaker.make_graph", "name": "make_graph", "type": {".class": "CallableType", "arg_kinds": [0, 0], "arg_names": ["self", "gi"], "arg_types": ["graphatoms.structure.graph.GraphMaker", "graphatoms.structure.graph.GraphInput"], "bound_args": [], "fallback": "builtins.function", "implicit": false, "is_classmethod_class": false, "is_ellipsis_args": false, "name": "make_graph of GraphMaker", "ret_type": {".class": "AnyType"}, "variables": []}}}, "make_unweighted_canonical": {".class": "SymbolTableNode", "kind": "Mdef", "node": {".class": "FuncDef", "arg_kinds": [0, 0], "arg_names": ["self", "gi"], "flags": [], "fullname": "graphatoms.structure.graph.GraphMaker.make_unweighted_canonical", "name": "make_unweighted_canonical", "type": {".class": "CallableType", "arg_kinds": [0, 0], "arg_names": ["self", "gi"], "arg_types": ["graphatoms.structure.graph.GraphMaker", "graphatoms.structure.graph.GraphInput"], "bound_args": [], "fallback": "builtins.function", "implicit": false, "is_classmethod_class": false, "is_ellipsis_args": false, "name": "make_unweighted_canonical of GraphMaker", "ret_type": "builtins.str", "variables": []}}}, "many_bond_order_analysis": {".class": "SymbolTableNode", "kind": "Mdef", "node": {".class": "FuncDef", "arg_kinds": [0, 0], "arg_names": ["self", "gi"], "flags": [], "fullname": "graphatoms.structure.graph.GraphMaker.many_bond_order_analysis", "name": "many_bond_order_analysis", "type": {".class": "CallableType", "arg_kinds": [0, 0], "arg_names": ["self", "gi"], "arg_types": ["graphatoms.structure.graph.GraphMaker", "graphatoms.structure.graph.GraphInput"], "bound_args": [], "fallback": "builtins.function", "implicit": false, "is_classmethod_class": false, "is_ellipsis_args": false, "name": "many_bond_order_analysis of GraphMaker", "ret_type": {".class": "NoneTyp"}, "variables": []}}}, "many_plotly_atoms": {".class": "SymbolTableNode", "kind": "Mdef", "node": {".class": "FuncDef", "arg_kinds": [0, 0], "arg_names": ["self", "gi"], "flags": [], "fullname": "graphatoms.structure.graph.GraphMaker.many_plotly_atoms", "name": "many_plotly_atoms", "type": {".class": "CallableType", "arg_kinds": [0, 0], "arg_names": ["self", "gi"], "arg_types": ["graphatoms.structure.graph.GraphMaker", "graphatoms.structure.graph.GraphInput"], "bound_args": [], "fallback": "builtins.function", "implicit": false, "is_classmethod_class": false, "is_ellipsis_args": false, "name": "many_plotly_atoms of GraphMaker", "ret_type": {".class": "NoneTyp"}, "variables": []}}}, "min_bo": {".class": "SymbolTableNode", "implicit": true, "kind": "Mdef", "node": {".class": "Var", "flags": [], "fullname": "graphatoms.structure.graph.GraphMaker.min_bo", "name": "min_bo", "type": "builtins.float"}}, "plot_bond_order_analysis": {".class": "SymbolTableNode", "kind": "Mdef", "node": {".class": "FuncDef", "arg_kinds": [0, 0, 1, 1, 1, 1], "arg_names": ["self", "gi", "show_groups", "filt", "show", "atoms"], "flags": [], "fullname": "graphatoms.structure.graph.GraphMaker.plot_bond_order_analysis", "name": "plot_bond_order_analysis", "type": {".class": "CallableType", "arg_kinds": [0, 0, 1, 1, 1, 1], "arg_names": ["self", "gi", "show_groups", "filt", "show", "atoms"], "arg_types": ["graphatoms.structure.graph.GraphMaker", "graphatoms.structure.graph.GraphInput", "builtins.bool", {".class": "CallableType", "arg_kinds": [0], "arg_names": [null], "arg_types": [{".class": "AnyType"}], "bound_args": [], "fallback": "builtins.function", "implicit": false, "is_classmethod_class": false, "is_ellipsis_args": false, "name": null, "ret_type": "builtins.bool", "variables": []}, "builtins.bool", {".class": "UnionType", "items": [{".class": "AnyType"}, {".class": "NoneTyp"}]}], "bound_args": [], "fallback": "builtins.function", "implicit": false, "is_classmethod_class": false, "is_ellipsis_args": false, "name": "plot_bond_order_analysis of GraphMaker", "ret_type": {".class": "NoneTyp"}, "variables": []}}}, "plot_many_sum_of_bond_orders": {".class": "SymbolTableNode", "kind": "Mdef", "node": {".class": "FuncDef", "arg_kinds": [0, 0, 0], "arg_names": ["self", "gi", "show_index"], "flags": [], "fullname": "graphatoms.structure.graph.GraphMaker.plot_many_sum_of_bond_orders", "name": "plot_many_sum_of_bond_orders", "type": {".class": "CallableType", "arg_kinds": [0, 0, 0], "arg_names": ["self", "gi", "show_index"], "arg_types": ["graphatoms.structure.graph.GraphMaker", "graphatoms.structure.graph.GraphInput", "builtins.int"], "bound_args": [], "fallback": "builtins.function", "implicit": false, "is_classmethod_class": false, "is_ellipsis_args": false, "name": "plot_many_sum_of_bond_orders of GraphMaker", "ret_type": {".class": "NoneTyp"}, "variables": []}}}, "plot_plotly_atoms": {".class": "SymbolTableNode", "kind": "Mdef", "node": {".class": "FuncDef", "arg_kinds": [0, 0], "arg_names": ["self", "gi"], "flags": [], "fullname": "graphatoms.structure.graph.GraphMaker.plot_plotly_atoms", "name": "plot_plotly_atoms", "type": {".class": "CallableType", "arg_kinds": [0, 0], "arg_names": ["self", "gi"], "arg_types": ["graphatoms.structure.graph.GraphMaker", "graphatoms.structure.graph.GraphInput"], "bound_args": [], "fallback": "builtins.function", "implicit": false, "is_classmethod_class": false, "is_ellipsis_args": false, "name": "plot_plotly_atoms of GraphMaker", "ret_type": {".class": "AnyType"}, "variables": []}}}, "show_adj_heatmap": {".class": "SymbolTableNode", "kind": "Mdef", "node": {".class": "FuncDef", "arg_kinds": [0, 0], "arg_names": ["self", "gi"], "flags": [], "fullname": "graphatoms.structure.graph.GraphMaker.show_adj_heatmap", "name": "show_adj_heatmap", "type": {".class": "CallableType", "arg_kinds": [0, 0], "arg_names": ["self", "gi"], "arg_types": ["graphatoms.structure.graph.GraphMaker", "graphatoms.structure.graph.GraphInput"], "bound_args": [], "fallback": "builtins.function", "implicit": false, "is_classmethod_class": false, "is_ellipsis_args": false, "name": "show_adj_heatmap of GraphMaker", "ret_type": {".class": "NoneTyp"}, "variables": []}}}}, "protocol_members": null, "tuple_type": null, "type_vars": [], "typeddict_type": null}}, "Iterator": {".class": "SymbolTableNode", "cross_ref": "typing.Iterator", "kind": "Gdef"}, "List": {".class": "SymbolTableNode", "cross_ref": "builtins.list", "kind": "Gdef", "normalized": true}, "NeighborList": {".class": "SymbolTableNode", "kind": "Gdef", "node": {".class": "Var", "flags": ["is_ready", "is_suppressed_import"], "fullname": "graphatoms.structure.graph.NeighborList", "name": "NeighborList", "type": {".class": "AnyType"}}}, "Tuple": {".class": "SymbolTableNode", "cross_ref": "typing.Tuple", "kind": "Gdef"}, "__doc__": {".class": "SymbolTableNode", "kind": "Gdef", "node": {".class": "Var", "flags": ["is_ready"], "fullname": "graphatoms.structure.graph.__doc__", "name": "__doc__", "type": "builtins.str"}}, "__file__": {".class": "SymbolTableNode", "kind": "Gdef", "node": {".class": "Var", "flags": ["is_ready"], "fullname": "graphatoms.structure.graph.__file__", "name": "__file__", "type": "builtins.str"}}, "__name__": {".class": "SymbolTableNode", "kind": "Gdef", "node": {".class": "Var", "flags": ["is_ready"], "fullname": "graphatoms.structure.graph.__name__", "name": "__name__", "type": "builtins.str"}}, "__package__": {".class": "SymbolTableNode", "kind": "Gdef", "node": {".class": "Var", "flags": ["is_ready"], "fullname": "graphatoms.structure.graph.__package__", "name": "__package__", "type": "builtins.str"}}, "adsorbate_graphs": {".class": "SymbolTableNode", "kind": "Gdef", "node": {".class": "FuncDef", "arg_kinds": [1], "arg_names": ["i"], "flags": [], "fullname": "graphatoms.structure.graph.adsorbate_graphs", "name": "adsorbate_graphs", "type": {".class": "CallableType", "arg_kinds": [1], "arg_names": ["i"], "arg_types": ["builtins.int"], "bound_args": [], "fallback": "builtins.function", "implicit": false, "is_classmethod_class": false, "is_ellipsis_args": false, "name": "adsorbate_graphs", "ret_type": {".class": "TupleType", "fallback": {".class": "Instance", "args": [{".class": "AnyType"}], "type_ref": "builtins.tuple"}, "implicit": false, "items": [{".class": "AnyType"}, {".class": "Instance", "args": ["builtins.int"], "type_ref": "builtins.list"}]}, "variables": []}}}, "angle": {".class": "SymbolTableNode", "cross_ref": "graphatoms.misc.atoms.angle", "kind": "Gdef"}, "ase": {".class": "SymbolTableNode", "kind": "Gdef", "node": {".class": "Var", "flags": ["is_ready", "is_suppressed_import"], "fullname": "graphatoms.structure.graph.ase", "name": "ase", "type": {".class": "AnyType"}}}, "chemical_symbols": {".class": "SymbolTableNode", "kind": "Gdef", "node": {".class": "Var", "flags": ["is_ready", "is_suppressed_import"], "fullname": "graphatoms.structure.graph.chemical_symbols", "name": "chemical_symbols", "type": {".class": "AnyType"}}}, "collections": {".class": "SymbolTableNode", "cross_ref": "collections", "kind": "ModuleRef"}, "copy": {".class": "SymbolTableNode", "cross_ref": "copy", "kind": "ModuleRef"}, "dihedral": {".class": "SymbolTableNode", "cross_ref": "graphatoms.misc.atoms.dihedral", "kind": "Gdef"}, "example_graph": {".class": "SymbolTableNode", "kind": "Gdef", "node": {".class": "FuncDef", "arg_kinds": [1], "arg_names": ["i"], "flags": [], "fullname": "graphatoms.structure.graph.example_graph", "name": "example_graph", "type": {".class": "CallableType", "arg_kinds": [1], "arg_names": ["i"], "arg_types": ["builtins.int"], "bound_args": [], "fallback": "builtins.function", "implicit": false, "is_classmethod_class": false, "is_ellipsis_args": false, "name": "example_graph", "ret_type": {".class": "AnyType"}, "variables": []}}}, "flatten": {".class": "SymbolTableNode", "cross_ref": "graphatoms.misc.utilities.flatten", "kind": "Gdef"}, "get_analysis_folder": {".class": "SymbolTableNode", "kind": "Gdef", "node": {".class": "Var", "flags": ["is_ready", "is_suppressed_import"], "fullname": "graphatoms.structure.graph.get_analysis_folder", "name": "get_analysis_folder", "type": {".class": "AnyType"}}}, "get_sherlock_folder": {".class": "SymbolTableNode", "kind": "Gdef", "node": {".class": "Var", "flags": ["is_ready", "is_suppressed_import"], "fullname": "graphatoms.structure.graph.get_sherlock_folder", "name": "get_sherlock_folder", "type": {".class": "AnyType"}}}, "identity": {".class": "SymbolTableNode", "kind": "Gdef", "node": {".class": "Var", "flags": ["is_ready", "is_suppressed_import"], "fullname": "graphatoms.structure.graph.identity", "name": "identity", "type": {".class": "AnyType"}}}, "jmol": {".class": "SymbolTableNode", "kind": "Gdef", "node": {".class": "FuncDef", "arg_kinds": [0, 1], "arg_names": ["atoms", "tol"], "flags": [], "fullname": "graphatoms.structure.graph.jmol", "name": "jmol", "type": {".class": "CallableType", "arg_kinds": [0, 1], "arg_names": ["atoms", "tol"], "arg_types": [{".class": "AnyType"}, "builtins.float"], "bound_args": [], "fallback": "builtins.function", "implicit": false, "is_classmethod_class": false, "is_ellipsis_args": false, "name": "jmol", "ret_type": {".class": "Instance", "args": ["graphatoms.structure.graph.Edge"], "type_ref": "builtins.list"}, "variables": []}}}, "json": {".class": "SymbolTableNode", "cross_ref": "json", "kind": "ModuleRef"}, "match_indices": {".class": "SymbolTableNode", "cross_ref": "graphatoms.misc.atoms.match_indices", "kind": "Gdef"}, "math": {".class": "SymbolTableNode", "cross_ref": "math", "kind": "ModuleRef"}, "negate": {".class": "SymbolTableNode", "kind": "Gdef", "node": {".class": "Var", "flags": ["is_ready", "is_suppressed_import"], "fullname": "graphatoms.structure.graph.negate", "name": "negate", "type": {".class": "AnyType"}}}, "np": {".class": "SymbolTableNode", "kind": "Gdef", "node": {".class": "Var", "flags": ["is_ready", "is_suppressed_import"], "fullname": "graphatoms.structure.graph.np", "name": "np", "type": {".class": "AnyType"}}}, "nx": {".class": "SymbolTableNode", "kind": "Gdef", "node": {".class": "Var", "flags": ["is_ready", "is_suppressed_import"], "fullname": "graphatoms.structure.graph.nx", "name": "nx", "type": {".class": "AnyType"}}}, "os": {".class": "SymbolTableNode", "cross_ref": "os", "kind": "ModuleRef"}, "pb": {".class": "SymbolTableNode", "kind": "Gdef", "node": {".class": "Var", "flags": ["is_ready", "is_suppressed_import"], "fullname": "graphatoms.structure.graph.pb", "name": "pb", "type": {".class": "AnyType"}}}, "replacer": {".class": "SymbolTableNode", "kind": "Gdef", "node": {".class": "Var", "flags": ["is_ready", "is_suppressed_import"], "fullname": "graphatoms.structure.graph.replacer", "name": "replacer", "type": {".class": "AnyType"}}}, "sys": {".class": "SymbolTableNode", "cross_ref": "sys", "kind": "ModuleRef"}, "test_adsorbate": {".class": "SymbolTableNode", "kind": "Gdef", "node": {".class": "FuncDef", "arg_kinds": [0], "arg_names": ["i"], "flags": [], "fullname": "graphatoms.structure.graph.test_adsorbate", "name": "test_adsorbate", "type": {".class": "CallableType", "arg_kinds": [0], "arg_names": ["i"], "arg_types": ["builtins.int"], "bound_args": [], "fallback": "builtins.function", "implicit": false, "is_classmethod_class": false, "is_ellipsis_args": false, "name": "test_adsorbate", "ret_type": {".class": "NoneTyp"}, "variables": []}}}, "test_subgraph": {".class": "SymbolTableNode", "kind": "Gdef", "node": {".class": "FuncDef", "arg_kinds": [1], "arg_names": ["p"], "flags": [], "fullname": "graphatoms.structure.graph.test_subgraph", "name": "test_subgraph", "type": {".class": "CallableType", "arg_kinds": [1], "arg_names": ["p"], "arg_types": ["builtins.int"], "bound_args": [], "fallback": "builtins.function", "implicit": false, "is_classmethod_class": false, "is_ellipsis_args": false, "name": "test_subgraph", "ret_type": {".class": "NoneTyp"}, "variables": []}}}, "true": {".class": "SymbolTableNode", "kind": "Gdef", "node": {".class": "Var", "flags": ["is_ready", "is_suppressed_import"], "fullname": "graphatoms.structure.graph.true", "name": "true", "type": {".class": "AnyType"}}}}, "path": "/Users/kbrown/graphatoms/structure/graph.py"}
